loniapi/__init__.py
loniapi/filedownloader.py
loniapi-0.0.6.dist-info/WHEEL
loniapi-0.0.6.dist-info/METADATA
loniapi-0.0.6.dist-info/RECORD
