Metadata-Version: 2.1
Name: loniapi
Version: 0.0.6
Summary: package to make calls to loni ida
License: MIT
Author: Hieu Do
Author-email: hieu.do@sagebionetworks.org
Requires-Python: >=3.7,<4.0
Classifier: License :: OSI Approved :: MIT License
Classifier: Programming Language :: Python :: 3
Classifier: Programming Language :: Python :: 3.7
Classifier: Programming Language :: Python :: 3.8
Classifier: Programming Language :: Python :: 3.9
Classifier: Programming Language :: Python :: 3.10
Classifier: Programming Language :: Python :: 3.11
Requires-Dist: pandas (>=1.2.0,<2.0.0)
Requires-Dist: requests (>=2.22.1,<3.0.0)
